qflashlight/qflashlight.py
qflashlight-0.2.0.data/data/share/applications/qflashlight.desktop
qflashlight-0.2.0.data/data/share/icons/hicolor/scalable/apps/qflashlight.svg
qflashlight-0.2.0.dist-info/DESCRIPTION.rst
qflashlight-0.2.0.dist-info/METADATA
qflashlight-0.2.0.dist-info/RECORD
qflashlight-0.2.0.dist-info/WHEEL
qflashlight-0.2.0.dist-info/entry_points.txt
qflashlight-0.2.0.dist-info/metadata.json
qflashlight-0.2.0.dist-info/top_level.txt
