Metadata-Version: 2.0
Name: qflashlight
Version: 0.2.0
Summary: Simple Qt-based fullscreen flashlight
Home-page: https://gitlab.com/Grumbel/qflashlight
Author: Ingo Ruhnke
Author-email: grumbel@gmail.com
License: UNKNOWN
Platform: UNKNOWN
